<?xml version="1.0" encoding="UTF-8"?>
<!DOCTYPE suite SYSTEM "http://testng.org/testng-1.0.dtd">
<suite name="TestSuite" thread-count="1" parallel="false">
    <test name="Test1">
        <parameter name="url"
            value="https://opensource-demo.orangehrmlive.com/index.php/auth/login" />
        <parameter name="uname" value="Admin" />
        <parameter name="upass" value="admin123" />
        <classes>
            <class name="com.pk_OrangeHRM.OrangeHRM_Login_Parameter"/>
        </classes>
    </test> <!-- Test -->
    
</suite> <!-- Suite -->